sysdash/__init__.py
sysdash/cli.py
sysdash/cli_mini.py
sysdash/collector.py
sysdash_cli-1.0.5.dist-info/licenses/LICENSE
sysdash_cli-1.0.5.dist-info/METADATA
sysdash_cli-1.0.5.dist-info/WHEEL
sysdash_cli-1.0.5.dist-info/entry_points.txt
sysdash_cli-1.0.5.dist-info/top_level.txt
sysdash_cli-1.0.5.dist-info/RECORD
