Metadata-Version: 2.4
Name: sysdash-cli
Version: 1.0.5
Summary: Real-time terminal-based system monitoring dashboard with graphs
Home-page: https://github.com/thulasiramk-2310/cli_metrics
Author: Thulasiram K
Author-email: Thulasiram K <kthulasiram231006@gmail.com>
License: MIT
Project-URL: Homepage, https://github.com/thulasiramk-2310/cli_metrics
Project-URL: Repository, https://github.com/thulasiramk-2310/cli_metrics
Project-URL: Issues, https://github.com/thulasiramk-2310/cli_metrics/issues
Keywords: monitoring,dashboard,system,cpu,memory,terminal,cli
Classifier: Development Status :: 4 - Beta
Classifier: Intended Audience :: Developers
Classifier: Intended Audience :: System Administrators
Classifier: Topic :: System :: Monitoring
Classifier: License :: OSI Approved :: MIT License
Classifier: Programming Language :: Python :: 3
Classifier: Operating System :: OS Independent
Requires-Python: >=3.7
License-File: LICENSE
Requires-Dist: psutil>=5.9.0
Requires-Dist: rich>=13.0.0
Provides-Extra: backend
Requires-Dist: requests>=2.0; extra == "backend"
Requires-Dist: websocket-client>=1.4.0; extra == "backend"
Dynamic: author
Dynamic: home-page
Dynamic: license-file
Dynamic: requires-python
